pypxr/__init__.py
pypxr/_uniaxial_reflect.py
pypxr/prsoxr_loader.py
pypxr/prsoxr_script_gen.py
pypxr/reflectivity.py
pypxr/structure.py
pypxr-0.0.1.dist-info/LICENSE
pypxr-0.0.1.dist-info/METADATA
pypxr-0.0.1.dist-info/WHEEL
pypxr-0.0.1.dist-info/top_level.txt
pypxr-0.0.1.dist-info/RECORD
