Metadata-Version: 2.1
Name: pypxr
Version: 0.0.1
Summary: A collection of utilities for reducing data and modeling Polarized Resonant Soft X-ray Reflectivity.
Home-page: https://github.com/usnistgov/P-RSoXR
Author: Thomas Ferron
Author-email: thomas.j.ferron@gmail.com
License: UNKNOWN
Project-URL: Github, https://github.com/usnistgov/P-RSoXR
Project-URL: Documentation, https://p-rsoxr.readthedocs.io/en/latest/
Platform: UNKNOWN
Classifier: Programming Language :: Python :: 3
Classifier: License :: OSI Approved :: MIT License
Classifier: Operating System :: OS Independent
Classifier: Intended Audience :: Science/Research
Classifier: License :: Freely Distributable
Classifier: Topic :: Scientific/Engineering :: Chemistry
Classifier: Topic :: Scientific/Engineering :: Physics
Requires-Python: >=3.6
License-File: LICENSE
Requires-Dist: numpy
Requires-Dist: scipy
Requires-Dist: pandas
Requires-Dist: matplotlib
Requires-Dist: seaborn
Requires-Dist: astropy
Requires-Dist: h5py
Requires-Dist: xlrd
Requires-Dist: pytest
Requires-Dist: tqdm
Requires-Dist: uncertainties
Requires-Dist: attrs
Requires-Dist: periodictable
Requires-Dist: refnx
